jrnl2tumblr/__init__.py
jrnl2tumblr/__main__.py
jrnl2tumblr/importer.py
jrnl2tumblr/tumblr.py
tests/__init__.py
tests/test_importer.py
tests/test_tumblr.py
jrnl2tumblr-0.1.3.dist-info/LICENSE
jrnl2tumblr-0.1.3.dist-info/METADATA
jrnl2tumblr-0.1.3.dist-info/WHEEL
jrnl2tumblr-0.1.3.dist-info/entry_points.txt
jrnl2tumblr-0.1.3.dist-info/top_level.txt
jrnl2tumblr-0.1.3.dist-info/RECORD
