Metadata-Version: 2.1
Name: jrnl2tumblr
Version: 0.1.3
Summary: Publish your jrnl entries on your Tumblr.
Home-page: https://github.com/eigenric/jrnl2tumblr
Author: Ricardo Ruiz Fernández de Alba
Author-email: ricardoruizfdez@gmail.com
Classifier: Programming Language :: Python :: 3
Classifier: License :: OSI Approved :: MIT License
Classifier: Operating System :: OS Independent
Requires-Python: >=3.6
License-File: LICENSE
Requires-Dist: pytumblr
